LICENSE
README.md
setup.cfg
setup.py
empirical_calibration/__init__.py
empirical_calibration/core.py
empirical_calibration/core_test.py
empirical_calibration.egg-info/PKG-INFO
empirical_calibration.egg-info/SOURCES.txt
empirical_calibration.egg-info/dependency_links.txt
empirical_calibration.egg-info/requires.txt
empirical_calibration.egg-info/top_level.txt
empirical_calibration/data/__init__.py
empirical_calibration/data/kang_schafer.py
empirical_calibration/data/kang_schafer_test.py
empirical_calibration/data/lalonde.py